pixflow/__init__.py
pixflow/processing/__init__.py
pixflow/processing/combination.py
pixflow/processing/transformation.py
pixflow/utils/__init__.py
pixflow/utils/io.py
pixflow/utils/plot.py
pixflow-0.2.0.dist-info/licenses/LICENSE.txt
pixflow-0.2.0.dist-info/METADATA
pixflow-0.2.0.dist-info/WHEEL
pixflow-0.2.0.dist-info/top_level.txt
pixflow-0.2.0.dist-info/RECORD
