Metadata-Version: 2.4
Name: pixflow
Version: 0.2.0
Summary: A simple image processing toolkit for resizing, histogram transfer, and difference detection.
Home-page: https://github.com/A-Chioquetta/pixflow
Author: Alessandra Chioquetta
Classifier: Programming Language :: Python :: 3
Classifier: License :: OSI Approved :: MIT License
Classifier: Operating System :: OS Independent
Requires-Python: >=3.7
License-File: LICENSE.txt
Requires-Dist: numpy
Requires-Dist: matplotlib
Requires-Dist: scikit-image>=0.16.1
Dynamic: author
Dynamic: classifier
Dynamic: description
Dynamic: description-content-type
Dynamic: home-page
Dynamic: license-file
Dynamic: requires-dist
Dynamic: requires-python
Dynamic: summary
